mjcgraph/__init__.py
mjcgraph/draw.py
mjcgraph/digraph/__init__.py
mjcgraph/digraph/cycle.py
mjcgraph/digraph/ddfo.py
mjcgraph/digraph/digraph.py
mjcgraph/digraph/digraphdfs.py
mjcgraph/digraph/ksscc.py
mjcgraph/digraph/regex.py
mjcgraph/digraph/symboldigraph.py
mjcgraph/digraph/topological.py
mjcgraph/graph/__init__.py
mjcgraph/graph/bfs.py
mjcgraph/graph/dfs.py
mjcgraph/graph/graph.py
mjcgraph-0.2.0.dist-info/LICENSE
mjcgraph-0.2.0.dist-info/METADATA
mjcgraph-0.2.0.dist-info/WHEEL
mjcgraph-0.2.0.dist-info/top_level.txt
mjcgraph-0.2.0.dist-info/RECORD
