Metadata-Version: 2.1
Name: mjcgraph
Version: 0.2.0
Summary: Some graph algorithms and visualisations
Author-email: Morten Jagd Christensen <mortenjc@jcaps.com>
Project-URL: Homepage, https://github.com/mortenjc/pygraph
Project-URL: Documentation, https://mjcgraph-doc.readthedocs.io/en/latest/
Project-URL: Bug Tracker, https://github.com/mortenjc/pygraph/issues
Classifier: Programming Language :: Python :: 3
Classifier: License :: OSI Approved :: BSD License
Classifier: Operating System :: OS Independent
Requires-Python: >=3.7
License-File: LICENSE
